instance_config/__init__.py
instance_config/instance.py
instance_config/lock.py
instance_config/services.py
instance_config-0.1.2.dist-info/DESCRIPTION.rst
instance_config-0.1.2.dist-info/METADATA
instance_config-0.1.2.dist-info/RECORD
instance_config-0.1.2.dist-info/WHEEL
instance_config-0.1.2.dist-info/metadata.json
instance_config-0.1.2.dist-info/top_level.txt
instance_config-0.1.2.dist-info/zip-safe
