Metadata-Version: 2.0
Name: instance-config
Version: 0.1.2
Summary: A simple library using consul locks to do one-time configuration tasks on AWS instances.
Home-page: https://github.com/mlipscombe/instance-config
Author: Mark Lipscombe
Author-email: mark@lipscombe.com
License: BSD
Keywords: instance-config
Platform: UNKNOWN
Classifier: Development Status :: 5 - Production/Stable
Classifier: Intended Audience :: Developers
Classifier: License :: OSI Approved :: BSD License
Classifier: Programming Language :: Python :: 3
Classifier: Programming Language :: Python :: 3.3
Classifier: Programming Language :: Python :: 3.4
Classifier: Programming Language :: Python :: 3.5
Requires-Dist: boto3
Requires-Dist: credstash
Requires-Dist: python-consul
Requires-Dist: cached-property
Requires-Dist: consul-lock
